ProxiesGrabber/__init__.py
ProxiesGrabber/scraper.py
ProxiesGrabber-1.0.6.dist-info/METADATA
ProxiesGrabber-1.0.6.dist-info/WHEEL
ProxiesGrabber-1.0.6.dist-info/top_level.txt
ProxiesGrabber-1.0.6.dist-info/RECORD
