Metadata-Version: 2.1
Name: ProxiesGrabber
Version: 1.0.6
Summary: A Python package for scraping free proxy lists from various online sources.
Home-page: https://github.com/alfarttusie/ProxiesGrabber
Author: alfarttusie
Author-email: muhammed@alfarttusie.com
Classifier: Development Status :: 5 - Production/Stable
Classifier: Intended Audience :: Developers
Classifier: License :: OSI Approved :: MIT License
Classifier: Programming Language :: Python :: 3
Classifier: Programming Language :: Python :: 3.7
Classifier: Programming Language :: Python :: 3.8
Classifier: Programming Language :: Python :: 3.9
Classifier: Programming Language :: Python :: 3.10
Requires-Python: >=3.7
Requires-Dist: requests
